{
  "/Childsafenet/docs-a1a": {
    "__comp": "5e95c892",
    "__context": {
      "plugin": "aba21aa0"
    }
  },
  "/Childsafenet/docs-4d5": {
    "__comp": "a7bd4aaa",
    "__props": "99021f2e"
  },
  "/Childsafenet/docs-af2": {
    "__comp": "a94703ab"
  },
  "/Childsafenet/docs/-75e": {
    "__comp": "17896441",
    "content": "4edc808e"
  },
  "/Childsafenet/docs/ai-training-option-periodic-17d": {
    "__comp": "17896441",
    "content": "e139872e"
  },
  "/Childsafenet/docs/api-reference-832": {
    "__comp": "17896441",
    "content": "77266aba"
  },
  "/Childsafenet/docs/architecture-108": {
    "__comp": "17896441",
    "content": "fd532226"
  },
  "/Childsafenet/docs/backlog-537": {
    "__comp": "17896441",
    "content": "0236cc39"
  },
  "/Childsafenet/docs/contributing-4a9": {
    "__comp": "17896441",
    "content": "72a427b3"
  },
  "/Childsafenet/docs/extension-0b6": {
    "__comp": "17896441",
    "content": "cd919f6d"
  },
  "/Childsafenet/docs/faq-5ba": {
    "__comp": "17896441",
    "content": "ea313555"
  },
  "/Childsafenet/docs/getting-started-839": {
    "__comp": "17896441",
    "content": "3021cf83"
  },
  "/Childsafenet/docs/ml-evaluation-metrics-e48": {
    "__comp": "17896441",
    "content": "bfc7a7a9"
  },
  "/Childsafenet/docs/roadmap-3ac": {
    "__comp": "17896441",
    "content": "b5e9cae4"
  },
  "/Childsafenet/docs/security-891": {
    "__comp": "17896441",
    "content": "7d0180ef"
  },
  "/Childsafenet/docs/sponsor-6f9": {
    "__comp": "17896441",
    "content": "8967b5ba"
  },
  "/Childsafenet/docs/user-guide-admin-467": {
    "__comp": "17896441",
    "content": "868a66fc"
  },
  "/Childsafenet/docs/user-guide-parent-3d0": {
    "__comp": "17896441",
    "content": "3eb32b6e"
  },
  "/Childsafenet/-f48": {
    "__comp": "9dd8a0d2",
    "__context": {
      "plugin": "a7456010"
    },
    "config": "5e9f5e1a"
  }
}